GetOldTweets3/__init__.py
GetOldTweets3/manager/TweetCriteria.py
GetOldTweets3/manager/TweetManager.py
GetOldTweets3/manager/__init__.py
GetOldTweets3/models/Tweet.py
GetOldTweets3/models/__init__.py
GetOldTweets3-0.0.9.data/scripts/GetOldTweets3
GetOldTweets3-0.0.9.dist-info/METADATA
GetOldTweets3-0.0.9.dist-info/RECORD
GetOldTweets3-0.0.9.dist-info/WHEEL
GetOldTweets3-0.0.9.dist-info/top_level.txt
