Metadata-Version: 2.1
Name: GetOldTweets3
Version: 0.0.9
Summary: Get old tweets from Twitter
Home-page: https://github.com/Mottl/GetOldTweets3
Author: Dmitry Mottl
Author-email: dmitry.mottl@gmail.com
License: MIT
Keywords: twitter tweets
Platform: UNKNOWN
Classifier: Environment :: Console
Classifier: Programming Language :: Python :: 3
Classifier: Programming Language :: Python :: 3.4
Classifier: Programming Language :: Python :: 3.5
Classifier: Programming Language :: Python :: 3.6
Classifier: License :: OSI Approved :: MIT License
Classifier: Operating System :: OS Independent
Classifier: Topic :: Internet :: WWW/HTTP :: Dynamic Content :: CGI Tools/Libraries
Requires-Python: >=3.4
Requires-Dist: lxml (>=3.5.0)
Requires-Dist: pyquery (>=1.2.10)
